ez_zk_client/__init__.py
testing/__init__.py
testing/test_connect.py
testing/test_listen.py
testing/test_lock_resource.py
ez_zk_client-0.0.3.dist-info/METADATA
ez_zk_client-0.0.3.dist-info/WHEEL
ez_zk_client-0.0.3.dist-info/top_level.txt
ez_zk_client-0.0.3.dist-info/RECORD
