Metadata-Version: 2.1
Name: ez-zk-client
Version: 0.0.3
Summary: Using Kazoo to implement specific features of ZooKeeper, such as: program survival monitoring (alive), global configuration, single-point resource lock, and multi-selection resource lock.
Home-page: https://github.com/sheauren/ez_zk_client
Author: Sheauren Wang
Author-email: sheauren@gmail.com
License: UNKNOWN
Platform: UNKNOWN
Classifier: Programming Language :: Python :: 3.5
Classifier: License :: OSI Approved :: MIT License
Requires-Python: >=3.5
Requires-Dist: kazoo
